{"id":["cfa4a379-e982-4a0c-b7e7-5a980b2c396b"],"cam_id":"c18a0cd7-7ad9-4fb8-b40d-f8dc781cd8f8","algo_id":"2","snippet_id":"fbba16d7-afed-4ab6-a931-1e122650d5fe","rois":[[[0,360],[1280,360],[1280,720],[0,720]]],"id_account":"9e967539-6b73-451b-b236-bcc621c088e0","id_branch":"9e967539-6b73-451b-b236-bcc621c088e0","ffserver_ip":null,"yoloHandUrl":"tcp:\/\/c18a0-yolo_handle:10002","camera_res":[1280,720],"mysql_ip":"ubuntu_db_1","mysql_user":"graymatics","mysql_pwd":"graymatics","mysql_db":"gsate","output_path":0,"confidence":0.1,"alertVideo":{"run":0},"alert_img":1,"cam_name":"cctv_footage222321","input_path":"\/home\/resources\/recordings\/cctv_footage222321.mp4"}